<?xml version="1.0" encoding="UTF-8"?>
<beans xmlns="http://www.springframework.org/schema/beans"
	xmlns:xsi="http://www.w3.org/2001/XMLSchema-instance"
	xsi:schemaLocation="http://www.springframework.org/schema/beans http://www.springframework.org/schema/beans/spring-beans.xsd">






	<bean class="com.km.bean.Role" scope="prototype"/>
	<bean class="com.km.bean.Authority" scope="prototype"/>
	<bean class="com.km.bean.Organization" scope="prototype"/>
	<bean class="com.km.bean.User" scope="prototype"/>
	<bean class="com.km.bean.CostPlan" scope="prototype"/>
	<bean class="com.km.bean.MajorPlan" scope="prototype"/>
	<bean class="com.km.bean.Unit" scope="prototype"/>
	<bean class="com.km.bean.Student" scope="prototype"/>
	<bean class="com.km.bean.CostListDetail" scope="prototype"/>
	<bean class="com.km.bean.WipeCost" scope="prototype"/>
	<bean class="com.km.bean.WipeCostDetail" scope="prototype"/>
	<bean class="com.km.bean.AuditHistory" scope="prototype"/>
			
			
			
</beans>
